<BackupInst xmlns="http://www.microsoft.com/GroupPolicy/GPOOperations/Manifest"><GPOGuid><![CDATA[{D8512465-51EA-4A2A-AFEB-9322EFADA346}]]></GPOGuid><GPODomain><![CDATA[mvp.azureblog.pl]]></GPODomain><GPODomainGuid><![CDATA[{0fd097d3-c0ad-4e10-937f-14695d44ef51}]]></GPODomainGuid><GPODomainController><![CDATA[vm-dc-neu.mvp.azureblog.pl]]></GPODomainController><BackupTime><![CDATA[2021-09-29T10:26:41]]></BackupTime><ID><![CDATA[{72220AA3-C90F-49DB-8F90-73773D56E5A9}]]></ID><Comment><![CDATA[]]></Comment><GPODisplayName><![CDATA[Audit Key Events]]></GPODisplayName></BackupInst>
